{
  "meta": {
    "version": "1.0.0",
    "description": "四化 × 宮位 × 主星 推理矩陣",
    "canonicalPalaces": ["命宮", "兄弟宮", "夫妻宮", "子女宮", "財帛宮", "疾厄宮", "遷移宮", "僕役宮", "官祿宮", "田宅宮", "福德宮", "父母宮"],
    "canonicalMainStars": ["紫微", "天機", "太陽", "武曲", "天同", "廉貞", "天府", "太陰", "貪狼", "巨門", "天相", "天梁", "七殺", "破軍"],
    "canonicalTransforms": ["祿", "權", "科", "忌"]
  },
  "patterns": [
    {
      "patternId": "ji_puyi_qisha_break",
      "palace": "僕役宮",
      "mainStar": "七殺",
      "transform": "忌",
      "patternType": "pressure",
      "patternName": "合作破局型壓力",
      "psychology": "容忍度下降，容易從忍耐切到翻臉",
      "lifePattern": "合作低效、權責不清或拖延時，容易快速切割關係",
      "shockLevel": 2,
      "advice": "先把規則、權責與停損點講清楚，再談信任與感情。",
      "sensoryTags": ["原本能忍，突然不想忍了", "對拖延與模糊特別不耐", "合作現場氣壓驟降"]
    },
    {
      "patternId": "lu_puyi_qisha_expansion",
      "palace": "僕役宮",
      "mainStar": "七殺",
      "transform": "祿",
      "patternType": "growth",
      "patternName": "強勢合作放大",
      "psychology": "會吸引高效率、強能力、結果導向的人際合作",
      "lifePattern": "團隊或人脈能成為放大實力的場域，但合作關係偏快節奏、偏硬",
      "shockLevel": 1,
      "advice": "選夥伴比擴張更重要，寧可少而強，不要多而亂。",
      "sensoryTags": ["高效率的合作節奏", "人少但戰力強", "合作像打仗"]
    },
    {
      "patternId": "quan_guanlu_taiyang_lead",
      "palace": "官祿宮",
      "mainStar": "太陽",
      "transform": "權",
      "patternType": "power",
      "patternName": "站上前台的責任",
      "psychology": "會被推到更需要承擔、帶人、表態的位置",
      "lifePattern": "事業上不是你想不想主導，而是事情自然會落到你身上",
      "shockLevel": 1,
      "advice": "先決定你要負責到哪裡，否則責任會無上限擴張。",
      "sensoryTags": ["一直被找來定奪", "很難隱身", "壓力來自責任不是能力不足"]
    },
    {
      "patternId": "ji_guanlu_taiyang_burn",
      "palace": "官祿宮",
      "mainStar": "太陽",
      "transform": "忌",
      "patternType": "pressure",
      "patternName": "過度燃燒型事業壓力",
      "psychology": "會把角色、責任與價值感綁得很緊",
      "lifePattern": "表面像是在扛工作，實際上是在扛『我不能倒』的壓力",
      "shockLevel": 2,
      "advice": "先拆責任，再談表現；先分工，再談使命感。",
      "sensoryTags": ["白天撐住，晚上很累", "一直覺得不能退", "責任越扛越滿"]
    },
    {
      "patternId": "ji_fuqi_jumen_conflict",
      "palace": "夫妻宮",
      "mainStar": "巨門",
      "transform": "忌",
      "patternType": "pressure",
      "patternName": "關係誤解與冷戰",
      "psychology": "容易把不安翻成質疑，把受傷翻成爭辯",
      "lifePattern": "關係裡的壓力常不是沒有愛，而是講不清、越講越傷",
      "shockLevel": 2,
      "advice": "先停下來確認你是在表達需要，還是在防衛自己。",
      "sensoryTags": ["話越說越歪", "沉默比吵架更傷", "心裡很多話但出口全變味"]
    },
    {
      "patternId": "ji_fuqi_tiantong_withdraw",
      "palace": "夫妻宮",
      "mainStar": "天同",
      "transform": "忌",
      "patternType": "pressure",
      "patternName": "委屈退縮型關係壓力",
      "psychology": "表面想和氣，內在卻越來越委屈",
      "lifePattern": "關係裡容易為了維持平靜而吞忍，最後變成情緒淤積",
      "shockLevel": 1,
      "advice": "和氣不是壓抑，舒服不是逃避；要把真正的感受說出來。",
      "sensoryTags": ["表面沒事其實有事", "不想吵所以先忍", "忍久了突然不想理"]
    },
    {
      "patternId": "ji_tianzhai_wuqu_security",
      "palace": "田宅宮",
      "mainStar": "武曲",
      "transform": "忌",
      "patternType": "pressure",
      "patternName": "根基焦慮型壓力",
      "psychology": "安全感會變得非常現實，容易翻譯成資產、成本與掌控",
      "lifePattern": "很多焦慮表面像在管房子、管配置，底層其實是在怕根基不穩",
      "shockLevel": 2,
      "advice": "不要用過度控制取代真正的安定，先分清楚什麼是必要，什麼是補償。",
      "sensoryTags": ["反覆算成本", "對失控很敏感", "想把一切先守住"]
    },
    {
      "patternId": "ji_zinv_lianzhen_control",
      "palace": "子女宮",
      "mainStar": "廉貞",
      "transform": "忌",
      "patternType": "pressure",
      "patternName": "成果控制型壓力",
      "psychology": "會把焦慮投射到作品、孩子、專案或延伸成果上",
      "lifePattern": "表面像在要求品質，底層其實是在補安全感",
      "shockLevel": 2,
      "advice": "先分清楚你是在追求品質，還是在害怕失控。",
      "sensoryTags": ["很難放手", "越在意越想管", "成果一不如預期就焦躁"]
    },
    {
      "patternId": "lu_caibo_wuqu_accumulate",
      "palace": "財帛宮",
      "mainStar": "武曲",
      "transform": "祿",
      "patternType": "growth",
      "patternName": "穩定累積型財運",
      "psychology": "資源感建立在可計算、可持續、可管理",
      "lifePattern": "適合用紀律、制度與長線配置來放大財務成果",
      "shockLevel": 1,
      "advice": "把擅長的控制力用在配置，不要用在焦慮。",
      "sensoryTags": ["一步一步堆出來", "不愛空談只看結果", "重視長期回報"]
    },
    {
      "patternId": "quan_caibo_tanlang_expand",
      "palace": "財帛宮",
      "mainStar": "貪狼",
      "transform": "權",
      "patternType": "power",
      "patternName": "擴張型變現企圖",
      "psychology": "會更想把魅力、人脈、體驗與機會變成實際資源",
      "lifePattern": "財務上有較強企圖心，但也容易因慾望而加大風險",
      "shockLevel": 2,
      "advice": "擴張可以，但要先設上限；企圖心要搭配風控。",
      "sensoryTags": ["很想把機會吃下來", "社交也想變現", "越有機會越想加碼"]
    },
    {
      "patternId": "ji_jiee_ziwei_dignity_stress",
      "palace": "疾厄宮",
      "mainStar": "紫微",
      "transform": "忌",
      "patternType": "pressure",
      "patternName": "尊嚴型壓力上身",
      "psychology": "不願示弱、不想失態，壓力常先吞回身體裡",
      "lifePattern": "很多時候不是身體弱，而是自我要求太高，身體先替你說不行",
      "shockLevel": 2,
      "advice": "承認自己現在不想扛，不是失格，是止損。",
      "sensoryTags": ["表面很穩", "身體先抗議", "累了也不想說"]
    },
    {
      "patternId": "ji_jiee_tianji_overthink",
      "palace": "疾厄宮",
      "mainStar": "天機",
      "transform": "忌",
      "patternType": "pressure",
      "patternName": "思緒過載型耗損",
      "psychology": "壓力會先進入腦袋，再滲到身體",
      "lifePattern": "不是事情太多，而是腦子停不下來，久了身體就開始跟著抗議",
      "shockLevel": 2,
      "advice": "先讓思緒停，再談效率；不是所有問題都要今晚解完。",
      "sensoryTags": ["腦袋一直轉", "夜裡很難停", "肩頸先緊起來"]
    },
    {
      "patternId": "ke_fude_taiyin_refine",
      "palace": "福德宮",
      "mainStar": "太陰",
      "transform": "科",
      "patternType": "correction",
      "patternName": "內在整理與情緒辨識",
      "psychology": "會開始更細膩地看見自己的情緒與需求",
      "lifePattern": "這段時間適合修復、整理與重新理解自己的內在節奏",
      "shockLevel": 1,
      "advice": "把感受說清楚，會比一直撐著更有用。",
      "sensoryTags": ["慢慢安靜下來", "更看得懂自己", "想要真正休息"]
    },
    {
      "patternId": "lu_minggong_jumen_voice_resource",
      "palace": "命宮",
      "mainStar": "巨門",
      "transform": "祿",
      "patternType": "growth",
      "patternName": "觀點變現型主線",
      "psychology": "你的觀察、判斷與說清楚事情的能力會帶來資源",
      "lifePattern": "很多價值來自你看見別人沒看見的問題，並且願意把它說清楚",
      "shockLevel": 1,
      "advice": "不要只停在看懂，還要把洞察變成可被使用的價值。",
      "sensoryTags": ["一眼看到問題核心", "很會拆解模糊處", "觀點能換到資源"]
    },
    {
      "patternId": "quan_minggong_taiyang_identity_lead",
      "palace": "命宮",
      "mainStar": "太陽",
      "transform": "權",
      "patternType": "power",
      "patternName": "被推上前台的自我主導",
      "psychology": "你會更想定義自己是誰，也更容易被放到需要表態的位置。",
      "lifePattern": "這不是單純自信提升，而是你開始不能再躲在模糊裡。",
      "shockLevel": 1,
      "advice": "先決定你要成為誰，再決定哪些責任值得接。",
      "sensoryTags": ["越來越難低調", "外界期待變高", "得表態、得定義自己"]
    },
    {
      "patternId": "ke_minggong_wenchang_self_reorder",
      "palace": "命宮",
      "mainStar": "文昌",
      "transform": "科",
      "patternType": "correction",
      "patternName": "自我敘事重整",
      "psychology": "你會開始重寫自己的邏輯、表達與人生說明書。",
      "lifePattern": "這段時間不是要你變成別人，而是把原本散亂的自我認知整理清楚。",
      "shockLevel": 1,
      "advice": "先把話說清楚，再把路走穩。",
      "sensoryTags": ["開始整理人生脈絡", "想把很多事講明白", "重新定義自己"]
    },
    {
      "patternId": "ji_minggong_tianji_identity_anxiety",
      "palace": "命宮",
      "mainStar": "天機",
      "transform": "忌",
      "patternType": "pressure",
      "patternName": "自我定位焦慮",
      "psychology": "你會反覆懷疑自己是不是選對了方向。",
      "lifePattern": "表面像在思考未來，底層其實是在怕選錯而不敢定下來。",
      "shockLevel": 2,
      "advice": "先選一條可走的路，再讓行動修正，而不是等到百分之百確定才開始。",
      "sensoryTags": ["一直想，卻很難定", "每條路都覺得有代價", "方向感忽強忽弱"]
    },
    {
      "patternId": "lu_guanlu_taiyang_visibility",
      "palace": "官祿宮",
      "mainStar": "太陽",
      "transform": "祿",
      "patternType": "growth",
      "patternName": "可見度放大型事業",
      "psychology": "你的影響力、曝光度與對外代表性會帶來資源。",
      "lifePattern": "適合站到更看得見的位置，把專業、理念或角色推到前台。",
      "shockLevel": 1,
      "advice": "讓看見你的人知道你到底能解決什麼問題。",
      "sensoryTags": ["被更多人看見", "舞台感變強", "對外代表性上升"]
    },
    {
      "patternId": "ke_guanlu_tianliang_professional_refine",
      "palace": "官祿宮",
      "mainStar": "天梁",
      "transform": "科",
      "patternType": "correction",
      "patternName": "專業聲望定型",
      "psychology": "你會更在意專業名聲、可信度與被尊重的方式。",
      "lifePattern": "這段時間適合建立方法、制度與可長可久的專業定位。",
      "shockLevel": 1,
      "advice": "把經驗整理成可傳承的標準，而不是只靠臨場扛住。",
      "sensoryTags": ["想把經驗系統化", "更重視名聲", "專業邊界變清楚"]
    },
    {
      "patternId": "ji_guanlu_tianliang_moral_burden",
      "palace": "官祿宮",
      "mainStar": "天梁",
      "transform": "忌",
      "patternType": "pressure",
      "patternName": "道德型職責壓力",
      "psychology": "你容易把『我應該扛』當成不能拒絕的理由。",
      "lifePattern": "職場壓力常不是能力不夠，而是責任感太重、標準太高。",
      "shockLevel": 2,
      "advice": "守護別人之前，先界定你不該代扛的部分。",
      "sensoryTags": ["總覺得自己該處理", "不好意思拒絕", "壓力來自責任感"]
    },
    {
      "patternId": "quan_guanlu_wuqu_control",
      "palace": "官祿宮",
      "mainStar": "武曲",
      "transform": "權",
      "patternType": "power",
      "patternName": "資源掌控型事業",
      "psychology": "你會更想掌控流程、資源、節奏與結果。",
      "lifePattern": "適合扛實權、做決策、管資源，但也容易變得很難放手。",
      "shockLevel": 1,
      "advice": "掌控力要用在關鍵點，不要用在所有細節。",
      "sensoryTags": ["想把事情抓在手裡", "很看重效率", "對低效特別不耐"]
    },
    {
      "patternId": "lu_guanlu_wuqu_result_expand",
      "palace": "官祿宮",
      "mainStar": "武曲",
      "transform": "祿",
      "patternType": "growth",
      "patternName": "結果導向型升級",
      "psychology": "能把努力直接換成看得見的成果與資源。",
      "lifePattern": "這段時間做得越扎實，成果越容易被量化、累積與放大。",
      "shockLevel": 1,
      "advice": "用制度化成果替代重複硬扛。",
      "sensoryTags": ["成果可衡量", "回報較直接", "做多少比較看得見"]
    },
    {
      "patternId": "quan_fuqi_qisha_define_boundary",
      "palace": "夫妻宮",
      "mainStar": "七殺",
      "transform": "權",
      "patternType": "power",
      "patternName": "關係主導與界線重整",
      "psychology": "你會更想在關係裡講清楚規則、權責與底線。",
      "lifePattern": "這段時間關係不是不能親近，而是不能再模糊。",
      "shockLevel": 2,
      "advice": "先講邊界，再談承諾；先定規則，再談感覺。",
      "sensoryTags": ["不想再曖昧模糊", "很多事想一次講清", "界線感變強"]
    },
    {
      "patternId": "lu_fuqi_taiyin_soften",
      "palace": "夫妻宮",
      "mainStar": "太陰",
      "transform": "祿",
      "patternType": "growth",
      "patternName": "關係滋養與安撫",
      "psychology": "情感支持、照顧與被理解的資源會流進關係。",
      "lifePattern": "這段時間比較容易在關係中找到情緒依靠與柔軟支持。",
      "shockLevel": 1,
      "advice": "讓溫柔有出口，不要只期待對方自己懂。",
      "sensoryTags": ["關係比較有被接住感", "需要被理解", "情緒較容易流動"]
    },
    {
      "patternId": "ke_fuqi_tianxiang_balance",
      "palace": "夫妻宮",
      "mainStar": "天相",
      "transform": "科",
      "patternType": "correction",
      "patternName": "關係秩序修正",
      "psychology": "你會開始更理性地整理關係裡的公平、角色與互動模式。",
      "lifePattern": "這不是單純修補，而是重新理解什麼叫健康的關係分工。",
      "shockLevel": 1,
      "advice": "先把角色講清楚，很多誤會就不需要情緒化處理。",
      "sensoryTags": ["重新談規則", "想把關係弄順", "不再只靠默契撐"]
    },
    {
      "patternId": "ji_fuqi_tanlang_temptation",
      "palace": "夫妻宮",
      "mainStar": "貪狼",
      "transform": "忌",
      "patternType": "pressure",
      "patternName": "慾望拉扯型關係壓力",
      "psychology": "容易在關係裡同時想要刺激、自由與安全感。",
      "lifePattern": "關係的壓力常來自慾望與承諾拉扯，而不是單純愛不愛。",
      "shockLevel": 2,
      "advice": "先分清楚你想追求的是新鮮感，還是真正的親密。",
      "sensoryTags": ["又想靠近又想逃", "刺激感很強", "情緒與慾望互相拉扯"]
    },
    {
      "patternId": "lu_tianzhai_tianfu_foundation",
      "palace": "田宅宮",
      "mainStar": "天府",
      "transform": "祿",
      "patternType": "growth",
      "patternName": "安穩累積型根基",
      "psychology": "你會更容易透過穩定、管理與累積建立安全感。",
      "lifePattern": "家、資產、根基與生活結構容易成為可長可久的支持來源。",
      "shockLevel": 1,
      "advice": "穩定是優勢，但別把穩定誤認為不能動。",
      "sensoryTags": ["慢慢堆出安定感", "家與資源越來越穩", "想建立長久基礎"]
    },
    {
      "patternId": "quan_tianzhai_tianxiang_order",
      "palace": "田宅宮",
      "mainStar": "天相",
      "transform": "權",
      "patternType": "power",
      "patternName": "家內秩序主導",
      "psychology": "你會更想定義生活規則、居住秩序與安全邊界。",
      "lifePattern": "這段時間家庭或生活基地不是不能共享，而是你會更想掌握配置與節奏。",
      "shockLevel": 1,
      "advice": "秩序要服務生活，不要讓生活變成秩序的附庸。",
      "sensoryTags": ["很想把家裡整好", "對秩序敏感", "想掌控生活基地"]
    },
    {
      "patternId": "ke_tianzhai_taiyin_heal_home",
      "palace": "田宅宮",
      "mainStar": "太陰",
      "transform": "科",
      "patternType": "correction",
      "patternName": "內在安居修復",
      "psychology": "你會重新理解什麼樣的空間、節奏與居所真正能安放自己。",
      "lifePattern": "這段時間適合做生活整理、情緒修復與安全感重建。",
      "shockLevel": 1,
      "advice": "先讓空間能照顧你，再談它看起來像什麼。",
      "sensoryTags": ["開始整理居家節奏", "想住得更像自己", "空間與情緒一起修復"]
    },
    {
      "patternId": "ji_tianzhai_lianzhen_boundary",
      "palace": "田宅宮",
      "mainStar": "廉貞",
      "transform": "忌",
      "patternType": "pressure",
      "patternName": "家內權力與控制壓力",
      "psychology": "安全感容易和控制感綁在一起，對家中規則與界線特別敏感。",
      "lifePattern": "表面像是在守住家，底層其實是在防止失控與被侵犯。",
      "shockLevel": 2,
      "advice": "先分清楚你是在守護，還是在過度防禦。",
      "sensoryTags": ["家中氣氛容易緊", "對邊界很敏感", "想把規則抓緊"]
    },
    {
      "patternId": "lu_tianzhai_wuqu_asset_expand",
      "palace": "田宅宮",
      "mainStar": "武曲",
      "transform": "祿",
      "patternType": "growth",
      "patternName": "資產穩步累積",
      "psychology": "你會更傾向用現實配置與可計算方式建立根基。",
      "lifePattern": "房產、資源、生活基地或長期配置容易成為穩定增長的場域。",
      "shockLevel": 1,
      "advice": "把焦慮轉成規劃，讓根基成為支撐而不是枷鎖。",
      "sensoryTags": ["喜歡有數字感的安全", "資源慢慢堆", "穩定感較可見"]
    },
    {
      "patternId": "ke_caibo_tianji_strategy",
      "palace": "財帛宮",
      "mainStar": "天機",
      "transform": "科",
      "patternType": "correction",
      "patternName": "財務策略重整",
      "psychology": "你會開始更在意方法、資訊差、配置邏輯與風險判斷。",
      "lifePattern": "這段時間財務不是只看賺多少，而是要看怎麼賺、怎麼守、怎麼配置。",
      "shockLevel": 1,
      "advice": "先整理策略，再決定出手速度。",
      "sensoryTags": ["開始研究配置", "更想看懂機制", "不是沒機會，是想更聰明"]
    },
    {
      "patternId": "ji_caibo_jumen_doubt",
      "palace": "財帛宮",
      "mainStar": "巨門",
      "transform": "忌",
      "patternType": "pressure",
      "patternName": "財務懷疑與失準",
      "psychology": "你容易在資源判斷上過度懷疑，或因焦慮而講得很清楚卻做得不夠穩。",
      "lifePattern": "表面像是在小心風險，底層其實是怕判斷失準、怕吃虧、怕看錯。",
      "shockLevel": 2,
      "advice": "先定標準，再下結論；不要讓焦慮代替判斷。",
      "sensoryTags": ["一直想值不值得", "怕吃虧", "很怕看錯局"]
    },
    {
      "patternId": "ji_caibo_wuqu_defense",
      "palace": "財帛宮",
      "mainStar": "武曲",
      "transform": "忌",
      "patternType": "pressure",
      "patternName": "過度防守型財壓",
      "psychology": "你會把資源管理變成一種防禦姿態。",
      "lifePattern": "不是沒有能力賺，而是太怕失控，容易先把自己鎖住。",
      "shockLevel": 2,
      "advice": "資源管理不是只防守，還要保留流動與成長的空間。",
      "sensoryTags": ["對損失很敏感", "不太敢冒險", "先守再說的傾向強"]
    },
    {
      "patternId": "lu_caibo_taiyin_soft_income",
      "palace": "財帛宮",
      "mainStar": "太陰",
      "transform": "祿",
      "patternType": "growth",
      "patternName": "細水長流型財源",
      "psychology": "收入與資源更容易透過穩定、細膩、長期照顧型價值累積。",
      "lifePattern": "不一定一夕暴增，但容易形成持續、溫和、可長可久的資源來源。",
      "shockLevel": 1,
      "advice": "相信慢的價值，不要只被快錢吸引。",
      "sensoryTags": ["收入像慢慢滲進來", "穩定比爆衝重要", "長線感強"]
    },
    {
      "patternId": "lu_jiee_tianliang_repair",
      "palace": "疾厄宮",
      "mainStar": "天梁",
      "transform": "祿",
      "patternType": "growth",
      "patternName": "修復力與保養意識提升",
      "psychology": "你比較容易在身心議題上找到合適的方法與照顧資源。",
      "lifePattern": "這段時間有機會透過保養、休養、醫療或規律照顧，把狀態慢慢拉回來。",
      "shockLevel": 1,
      "advice": "有修復力，不代表可以繼續硬耗。",
      "sensoryTags": ["慢慢修回來", "開始在意保養", "願意好好照顧自己"]
    },
    {
      "patternId": "ke_jiee_taiyin_body_awareness",
      "palace": "疾厄宮",
      "mainStar": "太陰",
      "transform": "科",
      "patternType": "correction",
      "patternName": "身體感受辨識提升",
      "psychology": "你會更細膩地察覺情緒、睡眠、荷爾蒙與身體節律的關係。",
      "lifePattern": "這段時間不是症狀突然變多，而是你終於開始看懂身體在說什麼。",
      "shockLevel": 1,
      "advice": "把身體訊號當資料，不要等它變成抗議才處理。",
      "sensoryTags": ["開始注意節律", "比較感受到身體細節", "學著讀懂疲勞"]
    },
    {
      "patternId": "ji_jiee_lianzhen_inflammation",
      "palace": "疾厄宮",
      "mainStar": "廉貞",
      "transform": "忌",
      "patternType": "pressure",
      "patternName": "情緒發炎型耗損",
      "psychology": "壓力會從界線、衝突與不甘心，慢慢燒進身體。",
      "lifePattern": "表面像情緒問題，實際上常會變成發炎、上火、緊繃與耗竭。",
      "shockLevel": 2,
      "advice": "先處理衝突，不要只處理身體表面症狀。",
      "sensoryTags": ["火氣上來", "很難放鬆", "氣在身體裡卡著"]
    },
    {
      "patternId": "ji_fude_jumen_inner_noise",
      "palace": "福德宮",
      "mainStar": "巨門",
      "transform": "忌",
      "patternType": "pressure",
      "patternName": "內在雜訊過強",
      "psychology": "心裡會一直有聲音，反覆分析、反覆懷疑，很難真正放鬆。",
      "lifePattern": "不是外界太吵，而是內在的評論者太用力。",
      "shockLevel": 2,
      "advice": "先停止和自己辯論，再處理真正的問題。",
      "sensoryTags": ["很難真正安靜", "腦內一直講話", "躺下來也停不住"]
    },
    {
      "patternId": "lu_fude_tiantong_restore",
      "palace": "福德宮",
      "mainStar": "天同",
      "transform": "祿",
      "patternType": "growth",
      "patternName": "恢復力與安撫資源",
      "psychology": "你比較容易找到能讓自己恢復能量的環境與方法。",
      "lifePattern": "這段時間不一定沒壓力，但你更有機會找回舒服、柔軟與自我安撫的能力。",
      "shockLevel": 1,
      "advice": "讓舒服成為修復，不要讓舒服變成逃避。",
      "sensoryTags": ["終於比較能喘口氣", "有些事開始放下", "恢復感變強"]
    },
    {
      "patternId": "quan_fude_tanlang_desire_mind",
      "palace": "福德宮",
      "mainStar": "貪狼",
      "transform": "權",
      "patternType": "power",
      "patternName": "慾望主導內在節奏",
      "psychology": "你會更明顯地被想要的東西牽動情緒與思緒。",
      "lifePattern": "這段時間內在世界不是平靜，而是充滿渴望、比較與推進感。",
      "shockLevel": 2,
      "advice": "先看見真正想要的是什麼，不要只追求刺激本身。",
      "sensoryTags": ["心很忙", "很難完全靜下來", "很想要某些東西"]
    },
    {
      "patternId": "ji_fude_taiyin_withdraw",
      "palace": "福德宮",
      "mainStar": "太陰",
      "transform": "忌",
      "patternType": "pressure",
      "patternName": "內在耗弱與退縮",
      "psychology": "情緒容易往內縮，安全感下降時特別想把自己藏起來。",
      "lifePattern": "不是懶，而是內在能量不夠，心先退了。",
      "shockLevel": 2,
      "advice": "先補能量，再談面對；退一下不是失敗，是整理。",
      "sensoryTags": ["想躲起來", "情緒不太想見人", "心裡先縮回去"]
    },
    {
      "patternId": "lu_zinv_taiyang_output",
      "palace": "子女宮",
      "mainStar": "太陽",
      "transform": "祿",
      "patternType": "growth",
      "patternName": "創造輸出放大",
      "psychology": "你的創造力、帶領感與輸出能量更容易轉成成果。",
      "lifePattern": "孩子、作品、企劃、延伸成果容易成為被看見與被放大的地方。",
      "shockLevel": 1,
      "advice": "把輸出變成系統，而不是只靠一時熱度。",
      "sensoryTags": ["作品更容易被看見", "輸出感變強", "很有想把東西生出來的感覺"]
    },
    {
      "patternId": "ke_zinv_tianji_create_refine",
      "palace": "子女宮",
      "mainStar": "天機",
      "transform": "科",
      "patternType": "correction",
      "patternName": "創造方法優化",
      "psychology": "你會重新理解怎麼創造、怎麼教養、怎麼把產出做得更精準。",
      "lifePattern": "這不是停滯，而是創造方式升級前的整理期。",
      "shockLevel": 1,
      "advice": "先整理方法，再要求成果。",
      "sensoryTags": ["開始修流程", "想把產出變更聰明", "不想再用舊做法硬撐"]
    },
    {
      "patternId": "quan_zinv_tanlang_expand_offspring",
      "palace": "子女宮",
      "mainStar": "貪狼",
      "transform": "權",
      "patternType": "power",
      "patternName": "創造慾與延伸掌控",
      "psychology": "你會更想主導延伸成果、創造物與被自己生出來的東西。",
      "lifePattern": "這段時間的創造不是隨性玩玩，而是帶著明顯企圖心與掌控欲。",
      "shockLevel": 2,
      "advice": "企圖心可以有，但別讓它壓垮創造的樂趣。",
      "sensoryTags": ["很想把成果做大", "創造感很強", "會想管到細節"]
    },
    {
      "patternId": "quan_puyi_tianji_network_strategy",
      "palace": "僕役宮",
      "mainStar": "天機",
      "transform": "權",
      "patternType": "power",
      "patternName": "策略型人脈運作",
      "psychology": "你會更主動地安排合作、串聯資源與調度關係。",
      "lifePattern": "人際不只是來往，而是變成可以被策略性運用的系統。",
      "shockLevel": 1,
      "advice": "人脈要有節奏地用，不要每條線都同時拉。",
      "sensoryTags": ["開始盤點人脈", "想把關係接起來", "合作安排感變強"]
    },
    {
      "patternId": "ke_puyi_tianxiang_balance_group",
      "palace": "僕役宮",
      "mainStar": "天相",
      "transform": "科",
      "patternType": "correction",
      "patternName": "團隊秩序修正",
      "psychology": "你會更注意團隊裡的角色平衡、公平感與界線。",
      "lifePattern": "這段時間適合修正合作方式、重新安排分工與責任。",
      "shockLevel": 1,
      "advice": "先把角色講明白，很多合作問題就不必靠情緒解決。",
      "sensoryTags": ["想重新整理團隊秩序", "分工議題浮出來", "開始調整合作位置"]
    },
    {
      "patternId": "ji_puyi_tanlang_social_noise",
      "palace": "僕役宮",
      "mainStar": "貪狼",
      "transform": "忌",
      "patternType": "pressure",
      "patternName": "社交耗損與人情拉扯",
      "psychology": "人際中的熱鬧、情面與誘惑，容易變成耗能來源。",
      "lifePattern": "表面像機會很多，底層卻可能因為太多關係牽扯而失焦。",
      "shockLevel": 2,
      "advice": "先分清楚哪些人是資源，哪些只是噪音。",
      "sensoryTags": ["局很多但很累", "社交後更耗", "人情牽扯變重"]
    },
    {
      "patternId": "lu_qianyi_tianji_move_opportunity",
      "palace": "遷移宮",
      "mainStar": "天機",
      "transform": "祿",
      "patternType": "growth",
      "patternName": "位移帶來機會",
      "psychology": "外出、移動、換環境時更容易接上新資訊與新資源。",
      "lifePattern": "舞台不一定在原地，很多機會是移動後才開始打開。",
      "shockLevel": 1,
      "advice": "不要怕動，動起來才會看見新的路。",
      "sensoryTags": ["一離開原場域就比較活", "移動時腦袋變開", "外面比原地有機會"]
    },
    {
      "patternId": "quan_qianyi_qisha_breakthrough",
      "palace": "遷移宮",
      "mainStar": "七殺",
      "transform": "權",
      "patternType": "power",
      "patternName": "外部場域突破",
      "psychology": "你會更想在外部世界主動闖、主動定調、主動搶位置。",
      "lifePattern": "移動、轉場、換市場時容易進入高壓但高成長的狀態。",
      "shockLevel": 2,
      "advice": "突破可以快，但風險要先看清楚。",
      "sensoryTags": ["很想往外衝", "外部競爭感強", "轉場會逼出戰鬥狀態"]
    },
    {
      "patternId": "ke_qianyi_tianliang_guidance",
      "palace": "遷移宮",
      "mainStar": "天梁",
      "transform": "科",
      "patternType": "correction",
      "patternName": "外部導師與修正",
      "psychology": "在外部場域比較容易遇到給你提醒、觀點與修正的人。",
      "lifePattern": "移動不是單純換地方，而是幫你看見原本看不到的盲點。",
      "shockLevel": 1,
      "advice": "出門不只是找機會，也是在找修正自己的視角。",
      "sensoryTags": ["出外有提醒", "容易被點醒", "不同場域幫你看懂自己"]
    },
    {
      "patternId": "ji_qianyi_jumen_misread",
      "palace": "遷移宮",
      "mainStar": "巨門",
      "transform": "忌",
      "patternType": "pressure",
      "patternName": "外部誤解與判斷壓力",
      "psychology": "在新場域更容易因資訊不對稱、誤解或多想而卡住。",
      "lifePattern": "不是外面不能去，而是出去後更考驗你怎麼判斷與怎麼說話。",
      "shockLevel": 2,
      "advice": "先確認資訊，再下判斷；先聽懂，再開口。",
      "sensoryTags": ["怕看錯風向", "新場域容易不安", "講話容易被誤解"]
    },
    {
      "patternId": "lu_fumu_tianliang_support",
      "palace": "父母宮",
      "mainStar": "天梁",
      "transform": "祿",
      "patternType": "growth",
      "patternName": "權威支持與保護",
      "psychology": "你比較容易從長輩、制度、價值框架或權威系統中得到支持。",
      "lifePattern": "這段時間規範與秩序不一定是束縛，也可能是保護與資源來源。",
      "shockLevel": 1,
      "advice": "看見支持，不代表要失去自主；善用而不是依附。",
      "sensoryTags": ["有人罩著", "制度感變成支撐", "長輩或權威資源浮現"]
    },
    {
      "patternId": "quan_fumu_ziwei_authority",
      "palace": "父母宮",
      "mainStar": "紫微",
      "transform": "權",
      "patternType": "power",
      "patternName": "權威議題升高",
      "psychology": "你會更敏感於誰說了算、誰有決定權、誰在定義標準。",
      "lifePattern": "父母、長輩、制度或價值來源會成為需要重新拿回主導感的領域。",
      "shockLevel": 2,
      "advice": "主導不等於對抗，先把邊界講清楚。",
      "sensoryTags": ["很在意誰有決定權", "對權威敏感", "想拿回自己的位置"]
    },
    {
      "patternId": "ke_fumu_zuofu_role_adjust",
      "palace": "父母宮",
      "mainStar": "左輔",
      "transform": "科",
      "patternType": "correction",
      "patternName": "支援角色重整",
      "psychology": "你會重新理解自己在家族、長輩或權威系統中的輔助角色。",
      "lifePattern": "這段時間不是只能扛，也是在調整你要支援到哪裡、退到哪裡。",
      "shockLevel": 1,
      "advice": "支持別人之前，先界定你自己的角色。",
      "sensoryTags": ["開始重想自己在家族中的位置", "不想再無限支援", "角色邊界更清楚"]
    },
    {
      "patternId": "ji_fumu_wuqu_value_pressure",
      "palace": "父母宮",
      "mainStar": "武曲",
      "transform": "忌",
      "patternType": "pressure",
      "patternName": "價值框架壓力",
      "psychology": "你容易把長輩、規則或價值框架變成一種現實壓力與績效標準。",
      "lifePattern": "很多不舒服不是單純跟父母有關，而是你內化了一套很硬的『應該』。",
      "shockLevel": 2,
      "advice": "把別人的標準和你真正認同的價值分開。",
      "sensoryTags": ["覺得自己應該更好", "標準很硬", "很難放過自己"]
    },
    {
      "patternId": "lu_xiongdi_tianji_network_gain",
      "palace": "兄弟宮",
      "mainStar": "天機",
      "transform": "祿",
      "patternType": "growth",
      "patternName": "合作資訊資源",
      "psychology": "合作、人脈與同輩圈更容易帶來資訊與機會。",
      "lifePattern": "這段時間不是單打獨鬥最有利，而是懂得用同輩與合作網路放大自己。",
      "shockLevel": 1,
      "advice": "多連結，不必每件事都自己算。",
      "sensoryTags": ["資訊交換變多", "合作有機會", "同輩連結帶來資源"]
    },
    {
      "patternId": "quan_xiongdi_tianliang_role_weight",
      "palace": "兄弟宮",
      "mainStar": "天梁",
      "transform": "權",
      "patternType": "power",
      "patternName": "同輩責任上升",
      "psychology": "你會在同輩、手足或合作圈中扛起更明顯的責任。",
      "lifePattern": "這段時間你不是旁觀者，而是容易變成穩住局面的人。",
      "shockLevel": 1,
      "advice": "照顧他人之前，先界定你不是所有人的保護者。",
      "sensoryTags": ["常被推去扛責任", "同輩議題落到你身上", "很難完全抽身"]
    },
    {
      "patternId": "lu_guanlu_tianliang_reputation_gain",
      "palace": "官祿宮",
      "mainStar": "天梁",
      "transform": "祿",
      "patternType": "growth",
      "patternName": "聲望與信任累積",
      "psychology": "你的專業可信度、保護性角色與長線價值更容易被看見。",
      "lifePattern": "這段時間不是短期爆紅，而是靠穩定、可靠與判斷力累積職場資本。",
      "shockLevel": 1,
      "advice": "把值得被信任這件事，轉成可被看見的專業成果。",
      "sensoryTags": ["別人開始更信任你", "適合做顧問型角色", "聲望慢慢往上堆"]
    },
    {
      "patternId": "quan_guanlu_tianliang_guardian_lead",
      "palace": "官祿宮",
      "mainStar": "天梁",
      "transform": "權",
      "patternType": "power",
      "patternName": "守護者型主導",
      "psychology": "你會更傾向站到維護秩序、撐住局面與替人把關的位置。",
      "lifePattern": "職場上容易成為標準制定者、風險把關者或道德壓力承擔者。",
      "shockLevel": 1,
      "advice": "主導不等於全扛，規範要清楚，責任也要有邊界。",
      "sensoryTags": ["變成大家會來問的人", "容易扛下道德責任", "看不下去就想出手管"]
    },
    {
      "patternId": "ke_guanlu_jumen_message_refine",
      "palace": "官祿宮",
      "mainStar": "巨門",
      "transform": "科",
      "patternType": "correction",
      "patternName": "專業表達修正",
      "psychology": "你會更在意怎麼把複雜的東西說清楚、講對、講得有用。",
      "lifePattern": "這段時間職場不是只看能力，還看你怎麼論述、怎麼拆解問題、怎麼建立說服力。",
      "shockLevel": 1,
      "advice": "把批判力變成清晰的表達，而不是只停在質疑。",
      "sensoryTags": ["一直在修說法", "很想把事情講準", "專業力開始跟語言綁一起"]
    },
    {
      "patternId": "ji_guanlu_jumen_reputation_conflict",
      "palace": "官祿宮",
      "mainStar": "巨門",
      "transform": "忌",
      "patternType": "pressure",
      "patternName": "職場口舌與信任摩擦",
      "psychology": "你會對資訊、說法、誤解與職場氛圍特別敏感。",
      "lifePattern": "很多壓力不是工作本身太難，而是溝通成本變高、誤解變多、說了卻未必被正確理解。",
      "shockLevel": 2,
      "advice": "先校正訊息，再處理情緒；先讓話準，再讓話重。",
      "sensoryTags": ["很容易有話想說", "說了卻不一定被懂", "職場空氣感變得很重要"]
    },
    {
      "patternId": "ke_guanlu_wuqu_cost_restructure",
      "palace": "官祿宮",
      "mainStar": "武曲",
      "transform": "科",
      "patternType": "correction",
      "patternName": "成本與制度重整",
      "psychology": "你會更清楚看見職場中的浪費、低效與不必要成本。",
      "lifePattern": "這段時間適合重新整理流程、資源配置與衡量標準，讓工作更穩更省力。",
      "shockLevel": 1,
      "advice": "把想省的地方變成系統，不要只靠自己硬撐。",
      "sensoryTags": ["開始看不慣低效", "想把流程重整", "會很在意投入產出比"]
    },
    {
      "patternId": "ji_guanlu_wuqu_hard_control",
      "palace": "官祿宮",
      "mainStar": "武曲",
      "transform": "忌",
      "patternType": "pressure",
      "patternName": "過度控場型職壓",
      "psychology": "你會把焦慮轉成更強的控制與更硬的標準。",
      "lifePattern": "表面像是在要求品質，底層其實是在怕失誤、怕掉價、怕資源失控。",
      "shockLevel": 2,
      "advice": "先處理不安全感，再處理細節，不然控制只會越來越重。",
      "sensoryTags": ["什麼都想自己確認", "越忙越不放心別人", "標準變得很硬"]
    },
    {
      "patternId": "lu_fuqi_tianxiang_supportive_balance",
      "palace": "夫妻宮",
      "mainStar": "天相",
      "transform": "祿",
      "patternType": "growth",
      "patternName": "互補型關係滋養",
      "psychology": "關係裡較容易出現互補、照應與講道理的合作感。",
      "lifePattern": "伴侶或重要關係容易成為支持系統，而不是單純情緒來源。",
      "shockLevel": 1,
      "advice": "把互補變成制度化的照應，不要只靠臨場默契。",
      "sensoryTags": ["關係有隊友感", "比較能互相幫忙", "講理比對抗有用"]
    },
    {
      "patternId": "quan_fuqi_taiyin_emotional_definition",
      "palace": "夫妻宮",
      "mainStar": "太陰",
      "transform": "權",
      "patternType": "power",
      "patternName": "情感節奏主導",
      "psychology": "你會更想定義親密、照顧與情緒安全感的方式。",
      "lifePattern": "關係裡的主導不一定是大聲，而是誰在定義情緒規則與相處節奏。",
      "shockLevel": 1,
      "advice": "照顧感受可以，但別讓感受變成唯一標準。",
      "sensoryTags": ["更在意對方有沒有懂你", "想要重新定義親密方式", "情緒節奏變重要"]
    },
    {
      "patternId": "ke_fuqi_taiyin_soft_repair",
      "palace": "夫妻宮",
      "mainStar": "太陰",
      "transform": "科",
      "patternType": "correction",
      "patternName": "情緒理解與柔性修復",
      "psychology": "你會更細膩地看見關係裡的脆弱、需求與情緒暗流。",
      "lifePattern": "這段時間適合把沒說清楚的委屈、害怕與期待重新整理。",
      "shockLevel": 1,
      "advice": "先辨認感受，再決定要不要做結論。",
      "sensoryTags": ["比較看見細微情緒", "關係變得比較需要被理解", "很多委屈浮上來"]
    },
    {
      "patternId": "ji_fuqi_taiyin_emotional_sink",
      "palace": "夫妻宮",
      "mainStar": "太陰",
      "transform": "忌",
      "patternType": "pressure",
      "patternName": "情緒下沉型關係壓力",
      "psychology": "你容易在關係裡默默受傷、默默失望，最後越來越沉默。",
      "lifePattern": "表面像是沒事，底層其實是很多感受沒有被好好承接。",
      "shockLevel": 2,
      "advice": "不要等到情緒下沉到底才開口，那時通常已經太晚。",
      "sensoryTags": ["外表平靜，心裡其實冷掉", "很多話吞回去", "失望不是一次，是慢慢累積"]
    },
    {
      "patternId": "lu_fuqi_tanlang_charm_flow",
      "palace": "夫妻宮",
      "mainStar": "貪狼",
      "transform": "祿",
      "patternType": "growth",
      "patternName": "吸引力與互動活性提升",
      "psychology": "關係中的魅力、互動感與新鮮感較容易流動起來。",
      "lifePattern": "親密、曖昧、吸引與想要靠近的能量會比較明顯。",
      "shockLevel": 1,
      "advice": "讓吸引力成為連結，而不是只追求刺激。",
      "sensoryTags": ["關係變得比較有火花", "互動感變強", "容易被吸引、也容易吸引人"]
    },
    {
      "patternId": "quan_fuqi_tanlang_desire_control",
      "palace": "夫妻宮",
      "mainStar": "貪狼",
      "transform": "權",
      "patternType": "power",
      "patternName": "慾望主導關係節奏",
      "psychology": "你會更想主導親密、吸引與彼此投入的方式。",
      "lifePattern": "關係裡的拉扯容易圍繞在誰比較想要、誰定義靠近方式、誰拿主導權。",
      "shockLevel": 2,
      "advice": "先分清楚想控制的是關係，還是自己的不安。",
      "sensoryTags": ["很想知道誰比較在意", "在乎互動主導權", "關係裡的慾望感變強"]
    },
    {
      "patternId": "lu_fuqi_qisha_fast_bond",
      "palace": "夫妻宮",
      "mainStar": "七殺",
      "transform": "祿",
      "patternType": "growth",
      "patternName": "高強度連結",
      "psychology": "關係裡容易出現很直接、很強烈、很快定調的互動。",
      "lifePattern": "吸引與切入速度都快，親密關係容易帶有高張力與高決斷感。",
      "shockLevel": 2,
      "advice": "強烈不等於穩定，快靠近也要留意是否真的合拍。",
      "sensoryTags": ["進展很快", "強烈吸引", "關係節奏偏硬偏快"]
    },
    {
      "patternId": "ke_fuqi_qisha_boundary_rebuild",
      "palace": "夫妻宮",
      "mainStar": "七殺",
      "transform": "科",
      "patternType": "correction",
      "patternName": "關係邊界重建",
      "psychology": "你會重新學習怎麼在親密中保有自我，也保有規則。",
      "lifePattern": "這段時間不是單純想分開，而是想把互動方式修到不再互相耗損。",
      "shockLevel": 1,
      "advice": "關係需要邊界，不然熱情很快就會變成消耗。",
      "sensoryTags": ["開始談界線", "想把相處方式修好", "不想再用情緒硬撞"]
    },
    {
      "patternId": "lu_jiee_ziwei_recovery_status",
      "palace": "疾厄宮",
      "mainStar": "紫微",
      "transform": "祿",
      "patternType": "growth",
      "patternName": "恢復尊嚴感的身心修復",
      "psychology": "當你願意承認自己需要照顧時，身體反而更容易回穩。",
      "lifePattern": "這段時間的修復不只是休息，而是重新建立身體與自我價值的關係。",
      "shockLevel": 1,
      "advice": "把照顧自己當成能力，不是軟弱。",
      "sensoryTags": ["終於肯照顧自己", "恢復不是丟臉", "身體感慢慢回來"]
    },
    {
      "patternId": "quan_jiee_ziwei_force_hold",
      "palace": "疾厄宮",
      "mainStar": "紫微",
      "transform": "權",
      "patternType": "power",
      "patternName": "硬撐型自我管理",
      "psychology": "你會更想掌握自己的身體、狀態與節奏，不想失控、不想倒下。",
      "lifePattern": "這種主導感能帶來紀律，也可能讓你忽略『撐住』本身就在耗損。",
      "shockLevel": 2,
      "advice": "自律有用，但不要把自律變成拒絕求助的理由。",
      "sensoryTags": ["很想控制狀態", "不想讓人看見脆弱", "努力把自己撐住"]
    },
    {
      "patternId": "lu_jiee_tianji_recover_by_adjust",
      "palace": "疾厄宮",
      "mainStar": "天機",
      "transform": "祿",
      "patternType": "growth",
      "patternName": "調整型修復力",
      "psychology": "只要方法對、節奏對，你的身體與精神其實有不錯的可調整性。",
      "lifePattern": "修復不是靠硬休，而是靠微調節奏、睡眠、資訊量與思緒負荷。",
      "shockLevel": 1,
      "advice": "找到自己的修復方法，比追求一次到位更重要。",
      "sensoryTags": ["有方法就恢復得快", "狀態跟節奏綁很緊", "調整比硬撐有效"]
    },
    {
      "patternId": "ke_jiee_lianzhen_conflict_awareness",
      "palace": "疾厄宮",
      "mainStar": "廉貞",
      "transform": "科",
      "patternType": "correction",
      "patternName": "衝突來源辨識",
      "psychology": "你會更明白哪些怒氣、控制感與不甘心，正在傷害身體。",
      "lifePattern": "這段時間的修正，不只是保養，而是看懂什麼情緒會讓你持續發炎。",
      "shockLevel": 1,
      "advice": "身體不是在跟你作對，它是在告訴你衝突還沒被處理。",
      "sensoryTags": ["比較看得懂自己的火氣", "開始連回情緒與身體", "知道哪類事最傷身"]
    },
    {
      "patternId": "ji_jiee_taiyin_hormonal_sink",
      "palace": "疾厄宮",
      "mainStar": "太陰",
      "transform": "忌",
      "patternType": "pressure",
      "patternName": "情緒荷爾蒙下沉",
      "psychology": "情緒、睡眠、荷爾蒙與安全感會互相拉扯，讓耗損變得很隱性。",
      "lifePattern": "不是大病大痛，而是慢慢失衡、慢慢累、慢慢提不起來。",
      "shockLevel": 2,
      "advice": "不要只怪自己懶或脆弱，先看見節律失衡本身就是壓力訊號。",
      "sensoryTags": ["很容易累", "睡不好也說不上哪裡不對", "情緒和身體一起往下掉"]
    },
    {
      "patternId": "lu_jiee_taiyin_nourish",
      "palace": "疾厄宮",
      "mainStar": "太陰",
      "transform": "祿",
      "patternType": "growth",
      "patternName": "滋養型恢復",
      "psychology": "身體與情緒比較容易因為被照顧、被滋養而回穩。",
      "lifePattern": "這段時間適合用溫和、持續、能安撫神經系統的方式修復自己。",
      "shockLevel": 1,
      "advice": "不是所有修復都要很硬核，溫柔也可以很有效。",
      "sensoryTags": ["慢慢被安撫", "比較能接住自己", "恢復感來自溫柔照顧"]
    },
    {
      "patternId": "lu_fude_jumen_insight_gain",
      "palace": "福德宮",
      "mainStar": "巨門",
      "transform": "祿",
      "patternType": "growth",
      "patternName": "洞察型內在資源",
      "psychology": "你越看得懂自己，越能從觀察、分析與思辨裡找到力量。",
      "lifePattern": "內在不是只有雜訊，也可能成為很深的理解力與判斷資源。",
      "shockLevel": 1,
      "advice": "把想太多變成想得透，內在就會從耗能變成資產。",
      "sensoryTags": ["愈整理愈看懂自己", "靜下來反而更有洞察", "思考開始有產值"]
    },
    {
      "patternId": "ke_fude_tiantong_rest_relearn",
      "palace": "福德宮",
      "mainStar": "天同",
      "transform": "科",
      "patternType": "correction",
      "patternName": "重新學會休息",
      "psychology": "你會開始重新理解什麼叫真正恢復，而不是只是暫時逃開。",
      "lifePattern": "這段時間適合修正休息方式、娛樂習慣與放鬆節奏。",
      "shockLevel": 1,
      "advice": "舒服不一定是逃避，但也不等於真的修復；要學會分辨。",
      "sensoryTags": ["開始重新安排休息", "不想再用麻痺當放鬆", "想真的回到舒服"]
    },
    {
      "patternId": "ji_fude_tiantong_soft_escape",
      "palace": "福德宮",
      "mainStar": "天同",
      "transform": "忌",
      "patternType": "pressure",
      "patternName": "溫柔逃避型內耗",
      "psychology": "你會更傾向用舒服、分心、先不要想來處理壓力。",
      "lifePattern": "表面像是休息，底層其實是在延後面對。",
      "shockLevel": 1,
      "advice": "先問自己現在是在修復，還是在逃避。",
      "sensoryTags": ["很想先不要面對", "想找舒服的地方躲一下", "休息完不一定真的恢復"]
    },
    {
      "patternId": "quan_fude_jumen_inner_judge",
      "palace": "福德宮",
      "mainStar": "巨門",
      "transform": "權",
      "patternType": "power",
      "patternName": "內在評論者掌權",
      "psychology": "你會更容易被自己的判斷、分析與內在聲音主導情緒節奏。",
      "lifePattern": "不是外界在壓你，而是你內在那個一直評分、一直分析的自己變得很大聲。",
      "shockLevel": 2,
      "advice": "讓思辨服務你，不要讓思辨統治你。",
      "sensoryTags": ["心裡那個評論者很大聲", "一件事會想很多層", "腦內法官感很強"]
    },
    {
      "patternId": "ji_zinv_tianji_output_scatter",
      "palace": "子女宮",
      "mainStar": "天機",
      "transform": "忌",
      "patternType": "pressure",
      "patternName": "創造分心與產出不穩",
      "psychology": "創造力不是沒有，而是太容易被太多想法拉散。",
      "lifePattern": "很多產出卡住不是因為不夠努力，而是方向切太快、思緒換太多。",
      "shockLevel": 2,
      "advice": "先收斂再輸出，先定主題再求多。",
      "sensoryTags": ["點子很多但不易收斂", "做一做又想改", "產出節奏忽快忽慢"]
    },
    {
      "patternId": "lu_zinv_tanlang_creative_desire",
      "palace": "子女宮",
      "mainStar": "貪狼",
      "transform": "祿",
      "patternType": "growth",
      "patternName": "創造慾與作品魅力放大",
      "psychology": "你更容易把想要表達、想要玩的、想要被看見的東西做成成果。",
      "lifePattern": "作品、企劃、孩子或延伸成果帶有更強的吸引力與感染力。",
      "shockLevel": 1,
      "advice": "讓魅力落地，不要只停在靈感與刺激。",
      "sensoryTags": ["很想做出有魅力的成果", "作品更有吸引力", "創造慾變強"]
    },
    {
      "patternId": "ke_zinv_taiyang_output_system",
      "palace": "子女宮",
      "mainStar": "太陽",
      "transform": "科",
      "patternType": "correction",
      "patternName": "輸出系統化",
      "psychology": "你會想把創造、教養、輸出與成果產製變得更有方法。",
      "lifePattern": "這段時間不是沒有火，而是開始把火收進系統。",
      "shockLevel": 1,
      "advice": "把熱情變成可重複的方法，成果才走得遠。",
      "sensoryTags": ["開始建立產出方法", "不想只靠靈感", "想把東西做得更穩"]
    },
    {
      "patternId": "ji_zinv_tanlang_overdesire",
      "palace": "子女宮",
      "mainStar": "貪狼",
      "transform": "忌",
      "patternType": "pressure",
      "patternName": "創造慾過載",
      "psychology": "你可能想做太多、想要太多、想同時抓很多成果。",
      "lifePattern": "表面像創造力旺，底層其實可能是焦躁與不滿足。",
      "shockLevel": 2,
      "advice": "先選真正想長大的那一個，不要每個都想救。",
      "sensoryTags": ["很想全都要", "越想做越焦躁", "想法和慾望一起往上衝"]
    },
    {
      "patternId": "ji_puyi_tianji_coordination_overload",
      "palace": "僕役宮",
      "mainStar": "天機",
      "transform": "忌",
      "patternType": "pressure",
      "patternName": "協調過載型人際壓力",
      "psychology": "你會很想把每個人、每件事、每條線都接好，最後卻先把自己耗掉。",
      "lifePattern": "合作壓力常來自資訊太多、協調太多、變因太多，而不是誰特別壞。",
      "shockLevel": 2,
      "advice": "先砍掉不必要的線，再處理重要的人。",
      "sensoryTags": ["一直在溝通協調", "覺得腦子被很多人佔用", "越想顧全越累"]
    },
    {
      "patternId": "lu_puyi_tanlang_social_gain",
      "palace": "僕役宮",
      "mainStar": "貪狼",
      "transform": "祿",
      "patternType": "growth",
      "patternName": "人際舞台放大",
      "psychology": "人脈、社交、活動與互動場域更容易帶來機會與資源。",
      "lifePattern": "這段時間不是關起門來最強，而是出去連結更有收穫。",
      "shockLevel": 1,
      "advice": "把社交變成有選擇的布局，不要只是忙。",
      "sensoryTags": ["局變多", "人脈帶來機會", "出去動一動就有收穫"]
    },
    {
      "patternId": "quan_puyi_tanlang_social_power",
      "palace": "僕役宮",
      "mainStar": "貪狼",
      "transform": "權",
      "patternType": "power",
      "patternName": "社交主導與場域掌控",
      "psychology": "你會更想掌握人際節奏、社交主導權與群體中的位置。",
      "lifePattern": "合作與朋友圈不只是互動，而是會變成權力與影響力運作的場域。",
      "shockLevel": 2,
      "advice": "先分清楚你要的是連結，還是控制。",
      "sensoryTags": ["很在意場上位置", "想主導人際節奏", "不喜歡自己在群體中失焦"]
    },
    {
      "patternId": "lu_qianyi_taiyin_support_outside",
      "palace": "遷移宮",
      "mainStar": "太陰",
      "transform": "祿",
      "patternType": "growth",
      "patternName": "外界溫柔資源",
      "psychology": "你在外部世界較容易得到照顧、支持與柔性資源。",
      "lifePattern": "移動、外出、換場域時，常會遇到讓你比較安心、比較被照顧的人事物。",
      "shockLevel": 1,
      "advice": "不要以為安全感只能在熟悉處，外面也可能有安放你的地方。",
      "sensoryTags": ["出外反而比較被照顧", "外面有溫柔資源", "移動後安心感增加"]
    },
    {
      "patternId": "ji_qianyi_tianji_unstable_move",
      "palace": "遷移宮",
      "mainStar": "天機",
      "transform": "忌",
      "patternType": "pressure",
      "patternName": "位移不穩與外界變因",
      "psychology": "外部世界的變動、資訊差與不確定感會特別容易讓你焦躁。",
      "lifePattern": "不是不能動，而是動的成本、變數與不確定性會放大。",
      "shockLevel": 2,
      "advice": "先做資訊準備，再做位移決定。",
      "sensoryTags": ["外面的不確定感很高", "移動前就開始焦慮", "變因感明顯"]
    },
    {
      "patternId": "ji_fumu_ziwei_authority_conflict",
      "palace": "父母宮",
      "mainStar": "紫微",
      "transform": "忌",
      "patternType": "pressure",
      "patternName": "權威與自我主權衝突",
      "psychology": "你會更敏感於權威壓力，也更容易覺得自己被定義、被規訓或被壓住。",
      "lifePattern": "很多不舒服不只是跟父母有關，而是你與權威、規範、標準來源的緊張關係被放大。",
      "shockLevel": 2,
      "advice": "先分清楚哪一部分是外在權威，哪一部分是你自己內化的壓力。",
      "sensoryTags": ["對上對下都很敏感", "被要求時容易卡住", "覺得自己的主導感被壓縮"]
    },
    {
      "patternId": "lu_fumu_zuofu_support_network",
      "palace": "父母宮",
      "mainStar": "左輔",
      "transform": "祿",
      "patternType": "growth",
      "patternName": "來自長輩系統的支援",
      "psychology": "你比較容易從長輩、家族或制度性支持中取得實際幫助。",
      "lifePattern": "這段時間權威系統不一定只帶來壓力，也可能給你資源與緩衝。",
      "shockLevel": 1,
      "advice": "看見支持，善用支持，但不要把自己交出去。",
      "sensoryTags": ["有人在後面幫你一把", "來自上位者的支持變多", "長輩資源可用"]
    },
    {
      "patternId": "ji_xiongdi_tianji_overcoordination",
      "palace": "兄弟宮",
      "mainStar": "天機",
      "transform": "忌",
      "patternType": "pressure",
      "patternName": "同輩協調與比較壓力",
      "psychology": "你容易在同輩、合作、手足或人脈圈中過度思考、過度比較、過度協調。",
      "lifePattern": "表面像人際問題，底層其實常是資訊太多、角色太多、分工太亂。",
      "shockLevel": 2,
      "advice": "先減少不必要的比較與協調成本，再談合作品質。",
      "sensoryTags": ["一直在想別人怎麼看", "合作很花腦力", "很容易心累"]
    }
  ]
}
