{
  "ziWei": "秩序的建立與尊嚴的維護，天生具備整合資源的上位者視角。",
  "tianJi": "極速的邏輯運算與多維度的變量分析，追求最優解。",
  "taiYang": "無私的能量輸出與價值傳播，以照亮他人為存在意義。",
  "wuQu": "剛性的執行力與結果導向，對物質與規則有極高的敏感度。",
  "tianTong": "情感的共鳴與和諧的追求，具備天然的療癒力與感知。",
  "lianZhen": "複雜秩序的守護與情感的囚禁，具備極強的原則感與敏銳度。",
  "tianFu": "穩定的儲存與防禦系統，追求物質與心理的安全邊界。",
  "taiYin": "沉澱的蓄水池與細膩的滋養，主導潛意識的直覺與情感。",
  "tanLang": "欲望的驅動與生命的變幻，是生命力最原始的擴張動力。",
  "juMen": "屏蔽後的穿透性觀察，致力於挖掘真相與邏輯的底層。",
  "tianXiang": "系統的平衡與完美的輔助，是維持社會關係的潤滑劑。",
  "tianLiang": "孤高的庇蔭者與規則的傳承，具備老靈魂般的超然視角。",
  "qiSha": "孤絕的突破力與結構性的摧毀，為了重建而存在的利劍。",
  "poJun": "翻新與冒險的極致動力，不惜粉碎現狀以追求新的可能。"
}
