{
  "wood.strong": "過度擴張。體感是肩膀緊繃、靜不下來。心理上極度追求成長，若停滯就會產生強烈的焦慮感。",
  "wood.weak": "生機匱乏。體感是易疲勞、晨起無力。心理上缺乏願景，做事容易三分鐘熱度，難以啟動長期計畫。",
  "fire.strong": "燃燒過旺。體感是心跳快、燥熱、睡眠淺。心理上情緒起伏大，容易在短時間內爆發毀滅性的熱情或憤怒。",
  "fire.weak": "動力失溫。體感是畏寒、手腳冰冷。心理上社交恐懼，對世界缺乏好奇心，難以感受到生命能量的喜悅。",
  "earth.strong": "過度沈重。體感是消化慢、身體沈重。心理上極度固執，拒絕改變，容易因過度包容他人而讓自己負荷過重。",
  "earth.weak": "地基動搖。體感是脾胃虛弱、易暈眩。心理上極度缺乏安全感，感覺自己像浮萍，難以在任何一段關係或工作中「落地」。",
  "metal.strong": "肅殺冷冽。體感是呼吸道敏感、皮膚緊繃。心理上追求絕對的對錯與效率，對自己與他人都有近乎殘酷的完美要求。",
  "metal.weak": "鋒芒斷裂。體感是容易過敏、聲帶無力。心理上優柔寡斷，遇到衝突就想退縮，無法建立有效的個人邊界。",
  "water.strong": "深淵無盡。體感是泌尿系統敏感、多夢。心理上欲望與智慧交織，容易想得太深、太遠，導致生活在漂泊的恐懼中。",
  "water.weak": "智慧乾枯。體感是骨骼痠痛、口乾。心理上邏輯僵化，轉不過彎，面對複雜的人際關係會感到嚴重的認知負載。"
}
