{
  "description": "輔星×12宮 20字內特質，copy_key=starPalace.{星名}_{宮名}，locale=zh-TW。可併入 content-zh-TW.starPalaces 或匯入 D1 ui_copy_texts。",
  "starPalaces": {
    "祿存_命宮": "穩健務實、重安全感、守成強、慢熱踏實、不冒進",
    "祿存_兄弟": "重界線、算得清、互動務實、情感保留、重責任分配",
    "祿存_夫妻": "伴侶節儉務實、重生活品質、踏實可靠、浪漫度低",
    "祿存_子女": "子女穩重懂事、重安全感、不冒險、金錢觀成熟",
    "祿存_財帛": "守財強、累積慢而厚、重儲蓄、忌投機、長期穩定",
    "祿存_疾厄": "復原慢、脾胃弱、需規律作息、體質穩定偏保守",
    "祿存_遷移": "外出保守、重安全、能存錢、社交謹慎、穩中求進",
    "祿存_僕役": "朋友精實、重互利界線、務實往來、圈子小但穩",
    "祿存_官祿": "工作踏實、適合長期耕耘、成績穩定、抗壓高",
    "祿存_田宅": "易積累房產、資產守得住、偏買不賣、小地主格局",
    "祿存_福德": "心求安定、不喜大起伏、享受簡單平靜、重底氣",
    "祿存_父母": "父母節儉務實、價值觀穩、會留資源、生活樸實",

    "天馬_命宮": "好動多變、坐不住、行動快、喜流動、需自由空間",
    "天馬_兄弟": "手足奔波、聚少離多、互動流動、各自忙碌發展",
    "天馬_夫妻": "伴侶常出差、距離感強、遠方姻緣、多奔波相處",
    "天馬_子女": "子女活潑外向、好動冒險、未來多往外發展",
    "天馬_財帛": "跑動越多越賺、財路靠移動、變動財強、遠方財旺",
    "天馬_疾厄": "容易心悸或腿傷、神經易緊繃、情緒起伏快",
    "天馬_遷移": "外地好運強、多貴人、多機會、遠比本地順利",
    "天馬_僕役": "朋友流動快、人脈廣、五湖四海、多變活絡",
    "天馬_官祿": "工作多變動、宜出差行業、節奏快、行動力強",
    "天馬_田宅": "容易搬家、多次更動、住處不固定、環境常變",
    "天馬_福德": "內心愛自由、討厭拘束、喜變化刺激、難長期停下",
    "天馬_父母": "早離家、與父母聚少、緣淡、成長多靠自己",

    "天刑_命宮": "原則強、嚴肅正直、不易親近、道德感重、易得罪人",
    "天刑_兄弟": "與手足易誤會、互動生硬、界線明、責任劃分強",
    "天刑_夫妻": "伴侶講道理、像法庭溝通、關係較嚴肅、衝突理性",
    "天刑_子女": "子女固執、拘謹、不易溝通、重規矩、慢熟",
    "天刑_財帛": "財務需透明、帳務要清楚、易法律糾紛、不可投機",
    "天刑_疾厄": "易開刀留疤、外傷機率高、體質偏硬、需留意意外",
    "天刑_遷移": "出外易罰單、法律問題較多、需守規則、勿冒險",
    "天刑_僕役": "朋友正派軍警多、衝突易起、互動偏硬、講原則",
    "天刑_官祿": "宜法律、醫療、技職、刀具業、需守規矩與流程",
    "天刑_田宅": "房產文件需確認、易糾紛、多法律程序、宜慎選",
    "天刑_福德": "內心孤獨壓力強、精神緊繃、偏理性、晚年向宗教",
    "天刑_父母": "父母嚴厲、高標準、紀律強、教育像軍事訓練",

    "天姚_命宮": "魅力強、浪漫感性、吸引力高、異性緣旺、外在亮眼",
    "天姚_兄弟": "手足迷人、有魅力、互動柔和、人緣好、氣氛佳",
    "天姚_夫妻": "伴侶外型好、魅力高、桃花多、相處浪漫但敏感",
    "天姚_子女": "子女活潑亮眼、異性緣好、氣質佳、多人喜愛",
    "天姚_財帛": "異性財旺、感性消費、偏財運好、美感創意賺錢",
    "天姚_疾厄": "需留意泌尿與荷爾蒙、情緒易受影響、感性起伏大",
    "天姚_遷移": "出外受異性助力、社交順利、人緣佳、公關強",
    "天姚_僕役": "朋友帥美、多藝術感、社交熱絡、感性互動多",
    "天姚_官祿": "適公關美容演藝、靠魅力與人際成功、曝光高",
    "天姚_田宅": "住處美感佳、重氛圍、喜佈置、家中常有喜氣",
    "天姚_福德": "享受浪漫、追求感性體驗、精神世界細膩敏感",
    "天姚_父母": "父母外型佳或社交廣、家庭氛圍輕鬆愉快",

    "左輔_命宮": "男性貴人強、做事順、易獲協助、貴氣穩、支援多",
    "左輔_兄弟": "手足或男同事能助力、互動穩、合作順、支持強",
    "左輔_夫妻": "伴侶務實能幫忙、做事可靠、支援度高、能共事",
    "左輔_子女": "子女懂事、能幫忙、領頭氣質、成熟早、互動好",
    "左輔_財帛": "男性帶財、賺錢穩、管道明確、財來有依靠",
    "左輔_疾厄": "遇好男醫生、康復快、處理有效、身體穩定",
    "左輔_遷移": "出外遇男貴人、助力大、發展順、多好連結",
    "左輔_僕役": "男性朋友可靠、有肩膀、互相扶持、長期穩定",
    "左輔_官祿": "男上司提拔、合作順、升遷穩、適合團隊合作",
    "左輔_田宅": "有人協助買房、交易順利、住處穩、資源不缺",
    "左輔_福德": "內心安定、有人支持、運勢平穩、心不孤單",
    "左輔_父母": "父親或男長輩助力強、支持度高、帶來資源",

    "右弼_命宮": "人緣佳、感受細膩、女性緣強、溫柔體貼、好相處",
    "右弼_兄弟": "姊妹或女同事貼心、互動和諧、情感支持強",
    "右弼_夫妻": "伴侶貼心柔和，但桃花較多、感情互動細膩敏感",
    "右弼_子女": "子女溫柔懂事、察言觀色、貼心、心思細膩",
    "右弼_財帛": "女性帶財、適合服務市場、細緻穩賺、小財不斷",
    "右弼_疾厄": "女性醫師照護佳、需注意內分泌、情緒敏感",
    "右弼_遷移": "出外受女性幫助多、運勢穩、社交順利易融入",
    "右弼_僕役": "女性友人可靠、情緒支撐強、人際柔和穩定",
    "右弼_官祿": "女主管賞識、工作細務順利、協作佳、穩定成長",
    "右弼_田宅": "住處溫馨、女性資源多、佈置細膩、家中和諧",
    "右弼_福德": "喜溫柔環境、情緒細膩、易受女性影響、重關懷",
    "右弼_父母": "母親或女性長輩疼愛多、細心照顧、關係柔和",

    "天魁_命宮": "男貴人強、氣質端莊、易得提拔、形象好、受尊重",
    "天魁_兄弟": "手足有人地位高、能協助、背景強、帶來支持",
    "天魁_夫妻": "伴侶正派背景好、提升地位、氣質端莊、可靠上進",
    "天魁_子女": "子女有出息、受長輩賞識、聰明懂事、氣質好",
    "天魁_財帛": "長輩帶財、正財穩、收入端正、資源來自上層",
    "天魁_疾厄": "遇名醫治療佳、復原快、體質端正穩定",
    "天魁_遷移": "出外遇伯樂、貴人多、機會提升、運勢順遂",
    "天魁_僕役": "正派朋友多、圈子乾淨、互相扶持、少負面干擾",
    "天魁_官祿": "易得男性上司賞識、升遷快、外在形象佳",
    "天魁_田宅": "易得長輩資源、買房順利、住處佳、環境好",
    "天魁_福德": "福報厚、遇難逢生、精神穩定、內心踏實",
    "天魁_父母": "父親或長輩權威強、地位高、助力多、背景深厚",

    "天鉞_命宮": "人緣佳、受女性長輩呵護、氣質溫和、貴氣柔潤",
    "天鉞_兄弟": "女性手足或同事暗中助力、互動柔和、支持強",
    "天鉞_夫妻": "伴侶氣質佳、長輩緣強、容易被照顧、婚姻偏溫柔",
    "天鉞_子女": "子女乖巧、異性緣好、受長輩喜愛、氣質乾淨",
    "天鉞_財帛": "女性帶財、偏財佳、有小道消息、細緻收益多",
    "天鉞_疾厄": "女醫師助力佳、修復快、需注意生殖內分泌",
    "天鉞_遷移": "外地遇女性貴人、受照顧、發展平穩、運勢柔順",
    "天鉞_僕役": "女性朋友可靠、溫暖、助力穩、社交不緊繃",
    "天鉞_官祿": "女性主管賞識、工作細緻穩、升遷靠柔性力量",
    "天鉞_田宅": "易得女性資源或母系房產、住處美好、氛圍佳",
    "天鉞_福德": "心靈柔軟、易受庇護、喜溫和環境、福報佳",
    "天鉞_父母": "母親或女性長輩保護強、情感連結深、助力多",

    "紅鸞_命宮": "外貌亮眼、人緣旺、喜事多、吸引力強、社交順",
    "紅鸞_兄弟": "手足明亮活潑、家中喜氣多、互動開朗",
    "紅鸞_夫妻": "伴侶外型佳、婚緣旺、感情順、氣氛愉快",
    "紅鸞_子女": "子女可愛亮眼、異性緣好、多喜事、多被喜愛",
    "紅鸞_財帛": "美感財旺、人緣財強、小確幸多、偏財佳",
    "紅鸞_疾厄": "留意血液與女性生理、整體健康偏輕小波動",
    "紅鸞_遷移": "出外受歡迎、公關運強、容易遇好人與喜事",
    "紅鸞_僕役": "朋友開朗亮眼、社交熱鬧、氛圍愉快有活力",
    "紅鸞_官祿": "適合美感、婚慶、公關業、魅力與人氣帶機會",
    "紅鸞_田宅": "家中布置漂亮、喜事多、氛圍溫馨、容易添喜",
    "紅鸞_福德": "樂觀享受、心態正面、生活儀式感強、喜氣常在",
    "紅鸞_父母": "父母外型佳、大方開朗、家庭氣氛愉快和諧",

    "天喜_命宮": "開朗樂觀、帶喜氣、好相處、氣場明亮、受歡迎",
    "天喜_兄弟": "手足常有喜事、聚會多、互動輕鬆愉快",
    "天喜_夫妻": "伴侶幽默好聊、感情輕鬆、相處愉快、氣氛佳",
    "天喜_子女": "子女活潑開心、帶來歡樂、氣氛明亮、有活力",
    "天喜_財帛": "偏財佳、財運輕鬆、小確幸多、賺錢靠好心情",
    "天喜_疾厄": "健康小波動、恢復快、精神愉快、活力佳",
    "天喜_遷移": "出外遇好事、好人多、旅運佳、動則有機會",
    "天喜_僕役": "朋友多玩伴、社交活躍、圈子熱鬧、氣氛好",
    "天喜_官祿": "適合娛樂、慶典、活動行業、帶歡樂創機會",
    "天喜_田宅": "家中常熱鬧、氛圍明亮、貴客多、喜氣環繞",
    "天喜_福德": "心境樂觀、容易滿足、精神輕鬆、幸福感強",
    "天喜_父母": "家庭氣氛活潑、父母開朗、互動輕鬆愉快",

    "文昌_命宮": "邏輯強、形象端正、重理性、學習力好、靠專業出頭",
    "文昌_兄弟": "手足重學歷、講規矩、重證照、互動偏理性",
    "文昌_夫妻": "伴侶理智講事實、溝通清晰、感情偏務實",
    "文昌_子女": "子女主動讀書、成績佳、重紀律、理解力強",
    "文昌_財帛": "靠證照合約賺錢、財務透明、重紀律、穩定入帳",
    "文昌_疾厄": "留意神經、大腦、皮膚問題、思慮過度易緊繃",
    "文昌_遷移": "異地靠名聲專業成長、適合讀書考試、發展順",
    "文昌_僕役": "朋友多專業人士、講原則、少情緒化、人際乾淨",
    "文昌_官祿": "適公務法律文職、重流程、升遷靠實力",
    "文昌_田宅": "重產權文件、家中愛書、空間整潔、條理分明",
    "文昌_福德": "精神追求邏輯秩序、喜閱讀、偏理性思考",
    "文昌_父母": "家教嚴、重教育背景、父母講規矩、有學術氣息",

    "文曲_命宮": "口才佳、幽默風趣、多才藝、感性強、好表達",
    "文曲_兄弟": "姊妹有才藝、情感豐富、互動柔和、語言力強",
    "文曲_夫妻": "伴侶浪漫有戲劇感、聰明伶俐、善溝通、感性多",
    "文曲_子女": "子女有表演天賦、嘴甜討喜、藝術感強",
    "文曲_財帛": "靠才藝美感賺錢、偏財佳、口才生財、有創意",
    "文曲_疾厄": "需留意內分泌與血液循環、情緒波動較明顯",
    "文曲_遷移": "出外靠口才人緣、多機會、適合演出社交",
    "文曲_僕役": "朋友多藝術型、情感豐富、社交靠感性",
    "文曲_官祿": "適合行銷、創意、演藝、溝通工作、魅力強",
    "文曲_田宅": "愛美感佈置、近水環境佳、空間有品味",
    "文曲_福德": "內心浪漫、享受藝術、重感性體驗、心靈細膩",
    "文曲_父母": "家庭風趣、氣氛活躍、母親多才多藝",

    "龍池_命宮": "氣質高雅、品味佳、有格調、呈現感強、外在亮眼",
    "龍池_兄弟": "手足氣質好、生活有品味、互動講究、審美佳",
    "龍池_夫妻": "伴侶品味高、重質感、生活講究、美感佳",
    "龍池_子女": "子女長相佳、有氣質、受喜愛、環境講究",
    "龍池_財帛": "美感財旺、靠質感賺錢、審美帶來收入",
    "龍池_疾厄": "注意皮膚外觀、壓力時易長瑕疵、需美感保養",
    "龍池_遷移": "出外提升名望、外界欣賞、容易被看見",
    "龍池_僕役": "朋友圈高質感、審美好、互動講究品味",
    "龍池_官祿": "適合美業、設計、公關、表演、提升形象",
    "龍池_田宅": "住處美觀、品味佳、裝潢講究、有質感",
    "龍池_福德": "內心追求美好、喜審美、重儀式感與氛圍",
    "龍池_父母": "父母品味好、審美強、生活品質佳",

    "鳳閣_命宮": "氣質高雅、品味佳、有格調、呈現感強、外在亮眼",
    "鳳閣_兄弟": "手足氣質好、生活有品味、互動講究、審美佳",
    "鳳閣_夫妻": "伴侶品味高、重質感、生活講究、美感佳",
    "鳳閣_子女": "子女長相佳、有氣質、受喜愛、環境講究",
    "鳳閣_財帛": "美感財旺、靠質感賺錢、審美帶來收入",
    "鳳閣_疾厄": "注意皮膚外觀、壓力時易長瑕疵、需美感保養",
    "鳳閣_遷移": "出外提升名望、外界欣賞、容易被看見",
    "鳳閣_僕役": "朋友圈高質感、審美好、互動講究品味",
    "鳳閣_官祿": "適合美業、設計、公關、表演、提升形象",
    "鳳閣_田宅": "住處美觀、品味佳、裝潢講究、有質感",
    "鳳閣_福德": "內心追求美好、喜審美、重儀式感與氛圍",
    "鳳閣_父母": "父母品味好、審美強、生活品質佳",

    "擎羊_命宮": "脾氣急、好勝強烈、行動快、果斷有衝力、易得罪人",
    "擎羊_兄弟": "手足易衝突、說話直、互動硬、競爭強、口角頻繁",
    "擎羊_夫妻": "伴侶刀子嘴、情緒急、易吵架、激烈愛恨、互動強烈",
    "擎羊_子女": "子女急躁好動、易受傷、固執、行動快",
    "擎羊_財帛": "破財快速、大進大出、競爭激烈、易衝動消費",
    "擎羊_疾厄": "易開刀見血、傷口明顯、火氣大、脊肌緊繃",
    "擎羊_遷移": "出外多爭執碰撞、血光機率增、需注意衝突",
    "擎羊_僕役": "朋友強勢、易反咬、衝突多、需慎選對象",
    "擎羊_官祿": "執行力強、適合高壓工作、行動快、有爆發力",
    "擎羊_田宅": "住處不安定、附近易有尖銳物、與祖產無緣",
    "擎羊_福德": "情緒澎湃、壓力大、內心憤慨多、需宣洩管道",
    "擎羊_父母": "長輩火爆、管教嚴、衝突多、關係容易緊張",

    "陀羅_命宮": "內心糾結、做事慢、完美主義、拖延、精神暗耗",
    "陀羅_兄弟": "與手足互動疏離、暗中較勁、合作拖延",
    "陀羅_夫妻": "伴侶拖拉磨嘰、冷戰多於爭吵、情緒悶著",
    "陀羅_子女": "子女晚得、性格沉悶、慢熱、固執、不主動",
    "陀羅_財帛": "財務停滯、錢滾錢心理、進帳慢、容易卡住",
    "陀羅_疾厄": "慢性病、久治不癒、牙脊問題、體質悶滯",
    "陀羅_遷移": "出外效率低、易卡關、容易迷路或錯過時機",
    "陀羅_僕役": "朋友猜忌重、暗耗多、互動不暢、小人較多",
    "陀羅_官祿": "工作拖延反覆、進度延宕、適合細工慢活",
    "陀羅_田宅": "買房過程冗長、易遇拖延糾紛、住處有瑕疵",
    "陀羅_福德": "心事放不下、長期糾結、難放鬆、精神耗能",
    "陀羅_父母": "家庭有長期糾紛、父母內向壓抑、互動疏離",

    "火星_命宮": "脾氣急躁、行動快、爆發力強、易衝動誤事、效率高",
    "火星_兄弟": "手足急性子、互動衝動、易爭吵、情緒起伏快",
    "火星_夫妻": "伴侶火爆直率、激情強烈、爭吵激烈、感情快進快出",
    "火星_子女": "子女脾氣強、易發炎或發燒、好動難管",
    "火星_財帛": "橫發橫破、見財快、花得更快、宜快節奏財務",
    "火星_疾厄": "易上火、發炎、皮膚紅腫、心跳快、需控情緒",
    "火星_遷移": "出外易染壞習慣、情緒放大、衝突可能增加",
    "火星_僕役": "朋友易衝動、脾氣硬、相處易爆點、互動強烈",
    "火星_官祿": "高壓工作佳、行動快、進度猛、適合快節奏",
    "火星_田宅": "住處多火氣、鄰近吵雜、注意用電與火災",
    "火星_福德": "內心躁動、易怒、能量不穩、需適時宣洩",
    "火星_父母": "父母脾氣火爆、家庭氣氛緊張、容易大吵",

    "鈴星_命宮": "愛碎念、疑心重、悶在心裡、情緒暗耗、易鑽牛角尖",
    "鈴星_兄弟": "手足間有猜忌、互動冷、暗中較細、少坦誠交流",
    "鈴星_夫妻": "伴侶愛念叨、翻舊帳、冷戰多、情緒壓抑",
    "鈴星_子女": "子女內向倔強、心事不說、悶著容易情緒波動",
    "鈴星_財帛": "財流隱晦、猶豫錯失機會、多算計、辛苦錢",
    "鈴星_疾厄": "易長異物（囊腫瘜肉）、神經衰弱、睡眠差",
    "鈴星_遷移": "出外悶悶不樂、易遇小人暗算、心防重",
    "鈴星_僕役": "朋友間互相冷刀子、小心暗箭、信任度低",
    "鈴星_官祿": "工作邊做邊懷疑、心裡暗耗、易覺被針對",
    "鈴星_田宅": "住處易小問題、漏水或異味、小破損拖很久",
    "鈴星_福德": "內心躁動多念、精神負擔重、容易自我內耗",
    "鈴星_父母": "父母愛抱怨、要求刻薄、情緒壓力大",

    "地空_命宮": "想法跳躍、理想化強、落地力弱、易空虛、精神敏感",
    "地空_兄弟": "手足緣淡、理念交流多、實質助力少、互動疏離",
    "地空_夫妻": "配偶精神飄忽、情感淡、溝通常斷層、緣分薄",
    "地空_子女": "子女聰明但怪、思維跳脫、與社會不合拍",
    "地空_財帛": "想法多落地少、財聚不大、觀念淡、不愛守財",
    "地空_疾厄": "容易心理壓力、憂鬱焦慮、神經衰弱、不易診斷",
    "地空_遷移": "出外波折多、白跑一趟感強、效率低",
    "地空_僕役": "朋友少、重理念不重實質、緣分淡、接觸不深",
    "地空_官祿": "適合創意宗教哲學、一般商業易因理想失敗",
    "地空_田宅": "與祖產無緣、房產計畫停想像、多空置寬敞",
    "地空_福德": "精神空虛感強、需心靈寄託、內心孤單敏感",
    "地空_父母": "父母思想怪、實際照顧弱、情感支持不足",

    "地劫_命宮": "做事賣命回報低、常有挫折感、努力被搶功、易破局",
    "地劫_兄弟": "手足互動破財多、常白忙、難合作、勞心勞力",
    "地劫_夫妻": "感情被拖累、付出多回收少、伴侶易成壓力來源",
    "地劫_子女": "子女耗心耗財、付出大回報小、易有損失",
    "地劫_財帛": "破財大洞、十投八賠、突發損失、越玩越空",
    "地劫_疾厄": "免疫崩弱、意外消耗、突發病、身體被榨乾感",
    "地劫_遷移": "出外易掉東西、迷路、挫折多、損失頻繁",
    "地劫_僕役": "朋友消耗大、小人多、金錢往來幾乎必賠",
    "地劫_官祿": "事業被劫功、快成功時翻船、破局率高",
    "地劫_田宅": "無祖產、房產易損失、抵押或不得不賣",
    "地劫_福德": "精神疲乏、感覺白忙、心力耗損大、內心易崩",
    "地劫_父母": "家境起伏大、父母助力薄、變動多、難依賴",

    "解神_命宮": "事情容易被化解、野心不強、衝勁弱、心境超脫",
    "解神_兄弟": "手足緣淡、爭執易化掉，但互動不深、助力少",
    "解神_夫妻": "感情易被「解掉」、冷戰消散、緣分薄、互動不穩",
    "解神_子女": "子女緣薄、長大各走各路、互不干擾、淡淡相處",
    "解神_財帛": "錢容易化掉、留不住、莫名支出、財務易散",
    "解神_疾厄": "能解災、病痛化小、運勢能逢凶化吉",
    "解神_遷移": "外出商機易化掉、白跑一趟、機會散掉",
    "解神_僕役": "朋友緣淡、關係淡去、無恩怨、互無牽掛",
    "解神_官祿": "工作不穩、動力弱、事情常被化掉、難長久",
    "解神_田宅": "房產守不住、常賣掉或變動、住處清靜無是非",
    "解神_福德": "心淡定、無欲、不執著、精神易放下、動力減弱",
    "解神_父母": "父母緣薄、彼此不干涉、互動淡但無衝突",

    "天巫_命宮": "有神秘天賦、易得傳承、直覺強、領悟快、靈性佳",
    "天巫_兄弟": "手足有人承家業、長輩助力強、技術傳承明顯",
    "天巫_夫妻": "伴侶帶遺產或技術、家族背景強、資源厚實",
    "天巫_子女": "子女能承衣缽、有天賦、受長輩特別疼愛",
    "天巫_財帛": "易得遺產財、長輩金援、特殊技術帶來收入",
    "天巫_疾厄": "注意遺傳性疾病、體質受祖上影響深",
    "天巫_遷移": "外地遇貴人手把手傳技、成長快、機緣特別",
    "天巫_僕役": "朋友傳遞好機會、技術分享多、關係深",
    "天巫_官祿": "升遷快、有上級傳位、技術承接能力強",
    "天巫_田宅": "可得祖產、房產傳承、家運深厚、有地基",
    "天巫_福德": "靈性深厚、有神秘感、福報足、心靈感應強",
    "天巫_父母": "父母有地位或技術傳承、對你提攜明顯",

    "孤辰_命宮": "孤僻高冷、情感封閉、內心不被理解、偏獨立",
    "孤辰_兄弟": "手足各忙各的、緣分淡、互動疏離、少依靠",
    "孤辰_夫妻": "感情冷淡、像室友、互動少激情、精神距離大",
    "孤辰_子女": "子女內向孤僻、難溝通、情感互動弱",
    "孤辰_財帛": "單打獨鬥賺錢、少合夥、靠自己累積",
    "孤辰_疾厄": "易因孤獨感生出憂鬱、胸胃壓力、情緒沉悶",
    "孤辰_遷移": "出外一人行、一人回、孤單感明顯",
    "孤辰_僕役": "朋友極少、緣淡、不愛社交、深交不多",
    "孤辰_官祿": "適合獨立作業、易被排擠、強調自我節奏",
    "孤辰_田宅": "喜清靜住處、人少環境、偏僻或安靜",
    "孤辰_福德": "內心封閉、靈魂孤獨、享受獨處但壓力大",
    "孤辰_父母": "父親性格固執孤僻、互動少、容易代溝",

    "寡宿_命宮": "情感淡薄、冷清孤寂、物欲低、與人保持距離",
    "寡宿_兄弟": "姊妹少、女性同事緣弱、互動冷、情感淡",
    "寡宿_夫妻": "婚姻冷淡、有名無實、伴侶常不在、情感距離大",
    "寡宿_子女": "子女少、或子女長大後不住家、情感疏離",
    "寡宿_財帛": "極度保守理財、不亂花、不冒險、重安全",
    "寡宿_疾厄": "女性生殖問題、生理波動、需長期照顧",
    "寡宿_遷移": "出外孤身、少依靠、旅程偏安靜孤獨",
    "寡宿_僕役": "朋友多單身者、社交冷清、互動不深",
    "寡宿_官祿": "工作清高但無實權、環境單調、情感稀薄",
    "寡宿_田宅": "住處人少、冷清、空間安靜、偏獨居氛圍",
    "寡宿_福德": "內心空泛、無欲無求、精神寂寞但習慣",
    "寡宿_父母": "母親冷感獨立、情感少交流、代溝深",

    "破碎_命宮": "做事易半途、情緒易受打擊、抗壓弱、小挫折多",
    "破碎_兄弟": "手足間有裂痕、合作易破局、感情時好時壞",
    "破碎_夫妻": "感情有裂痕、小吵不斷、熱情磨掉、需要修補",
    "破碎_子女": "子女易受傷、叛逆、情緒不穩、小波折多",
    "破碎_財帛": "常破小財、丟錢、小虧損、小洞不斷需修補",
    "破碎_疾厄": "小傷痕、牙齒骨骼問題多、小病不斷",
    "破碎_遷移": "行程易變、小意外多、計畫反覆、需留彈性",
    "破碎_僕役": "朋友易扯後腿、背後消耗、互動不穩",
    "破碎_官祿": "工作反覆、小錯多、案子卡關、差一步成功",
    "破碎_田宅": "房屋易漏水、破損、裝修不滿意、小問題多",
    "破碎_福德": "內心不安、小挫折多、精神碎裂感、需整理",
    "破碎_父母": "家中曾受損、父母關係不完整、互動不穩",

    "劫煞_命宮": "易遇競爭者、小人干擾、運勢起伏、需快速應對",
    "劫煞_兄弟": "手足或同事間暗搶資源、互動競爭、易有摩擦",
    "劫煞_夫妻": "感情易被介入、出現競爭者、感情波折",
    "劫煞_子女": "子女遇外來壓力、競爭強、需保護、易失衡",
    "劫煞_財帛": "突然破財、小人奪利、搶單事件多、易損失",
    "劫煞_疾厄": "突發小病、外來傷害、免疫波動、需防意外",
    "劫煞_遷移": "出外易遇意外、被搶機會、被競爭取代",
    "劫煞_僕役": "朋友間易背刺、暗搶功、互動不單純",
    "劫煞_官祿": "職場競爭強、小人多、成果易被拿走",
    "劫煞_田宅": "房產易被搶、外來壓力多、突發問題頻繁",
    "劫煞_福德": "內心不安、外界壓迫感強、精神緊張",
    "劫煞_父母": "家中曾遇損失或競爭、父母助力有限",

    "大耗_命宮": "耗能大、體力易空、金錢流失、需節制與規劃",
    "大耗_兄弟": "手足關係消耗、互動使你花錢或花力",
    "大耗_夫妻": "伴侶花費大、家庭開銷多、關係耗財",
    "大耗_子女": "教育花大錢、養育消耗多、心力負擔重",
    "大耗_財帛": "大筆開支、消費衝動、存款難累積",
    "大耗_疾厄": "體力透支、免疫下降、需長期補充休息",
    "大耗_遷移": "出外容易大花錢、旅行或移動成本高",
    "大耗_僕役": "朋友使你破財、情緒與金錢雙重消耗",
    "大耗_官祿": "工作耗能大、加班多、精神負荷高",
    "大耗_田宅": "房屋大修、漏水、大支出、資金流失",
    "大耗_福德": "精神空耗、內心疲乏、幸福感下降",
    "大耗_父母": "家庭需大筆資助、父母開銷高、負擔重",

    "蜚廉_命宮": "容易被議論、名譽波動、口舌是非多、需慎言行",
    "蜚廉_兄弟": "手足或同事間流言多、易誤會、需清楚界線",
    "蜚廉_夫妻": "感情被指指點點、外界干擾、需穩定心態",
    "蜚廉_子女": "子女名聲波動、被議論、需保護情緒",
    "蜚廉_財帛": "財務被評論、須避免張揚、口舌引破財",
    "蜚廉_疾厄": "因壓力出現小病、情緒因流言受影響",
    "蜚廉_遷移": "出外易遇誤會與口舌、名譽不穩、需低調",
    "蜚廉_僕役": "朋友圈是非多、背後議論、易受流言干擾",
    "蜚廉_官祿": "職場謠言多、名聲受挑戰、需潔身自愛",
    "蜚廉_田宅": "鄰里口舌、小事變大、需避免衝突",
    "蜚廉_福德": "內心受批評影響、精神不穩、需建立界線",
    "蜚廉_父母": "家庭曾有流言傷害、父母名聲受影響"
  }
}
